lotopy/__init__.py
lotopy/lotopy.py
LotoPy-0.1.2.dist-info/METADATA
LotoPy-0.1.2.dist-info/WHEEL
LotoPy-0.1.2.dist-info/top_level.txt
LotoPy-0.1.2.dist-info/RECORD
