Metadata-Version: 2.1
Name: LotoPy
Version: 0.1.2
Summary: pacote para geração de números aleatórios para jogos de loteria
Home-page: https://github.com/flaviorabelo/lotopy
Author: Flavio Rabelo
Author-email: flaviorab@gmail.com
License: UNKNOWN
Keywords: loteria aposta jogo aleatorio
Platform: UNKNOWN
Requires-Python: >=3.0
